hello_world_ly2/__init__.py
hello_world_ly2/tools/__init__.py
hello_world_ly2/tools/hello_world_tool.py
hello_world_ly2/tools/utils.py
hello_world_ly2/yamls/hello_world_tool.yaml
hello_world_ly2-0.0.1.dist-info/METADATA
hello_world_ly2-0.0.1.dist-info/WHEEL
hello_world_ly2-0.0.1.dist-info/entry_points.txt
hello_world_ly2-0.0.1.dist-info/top_level.txt
hello_world_ly2-0.0.1.dist-info/RECORD
